Leveragers/__init__.py
Leveragers/uwulogger.py
uwulogger-1.2.dist-info/LICENSE
uwulogger-1.2.dist-info/METADATA
uwulogger-1.2.dist-info/WHEEL
uwulogger-1.2.dist-info/top_level.txt
uwulogger-1.2.dist-info/RECORD
